magic 03f30d0a
<code>
   <argcount> 0 </argcount>
   <nlocals> 0</nlocals>
   <stacksize> 3</stacksize>
   <flags> 0040</flags>
   <code>
      6400006401006402006703005a0000781300650000445d0b005a01006501
      0047487116005764030053
   </code>
   <dis>
  1           0 LOAD_CONST               0 (1)
              3 LOAD_CONST               1 (2)
              6 LOAD_CONST               2 (3)
              9 BUILD_LIST               3
             12 STORE_NAME               0 (l)

  2          15 SETUP_LOOP              19 (to 37)
             18 LOAD_NAME                0 (l)
             21 GET_ITER            
        >>   22 FOR_ITER                11 (to 36)
             25 STORE_NAME               1 (i)

  3          28 LOAD_NAME                1 (i)
             31 PRINT_ITEM          
             32 PRINT_NEWLINE       
             33 JUMP_ABSOLUTE           22
        >>   36 POP_BLOCK           
        >>   37 LOAD_CONST               3 (None)
             40 RETURN_VALUE        
   </dis>
   <names> ('l', 'i')</names>
   <varnames> ()</varnames>
   <freevars> ()</freevars>
   <cellvars> ()</cellvars>
   <filename> 'iter_test.py'</filename>
   <name> '<module>'</name>
   <firstlineno> 1</firstlineno>
   <consts>
      1
      2
      3
      None
   </consts>
   <lnotab> 0f010d01</lnotab>
</code>
