magic 03f30d0a
<code>
   <argcount> 0 </argcount>
   <nlocals> 0</nlocals>
   <stacksize> 5</stacksize>
   <flags> 0040</flags>
   <code>
      6400008400005a0000650000640100640200640300640400830002016405
      0053
   </code>
   <dis>
  1           0 LOAD_CONST               0 (<code object foo at 0x10a720c30, file "test_kw_param.py", line 1>)
              3 MAKE_FUNCTION            0
              6 STORE_NAME               0 (foo)

  7           9 LOAD_NAME                0 (foo)
             12 LOAD_CONST               1 ('a')
             15 LOAD_CONST               2 (1)
             18 LOAD_CONST               3 ('b')
             21 LOAD_CONST               4 (2)
             24 CALL_FUNCTION          512
             27 POP_TOP             
             28 LOAD_CONST               5 (None)
             31 RETURN_VALUE        
   </dis>
   <names> ('foo',)</names>
   <varnames> ()</varnames>
   <freevars> ()</freevars>
   <cellvars> ()</cellvars>
   <filename> 'test_kw_param.py'</filename>
   <name> '<module>'</name>
   <firstlineno> 1</firstlineno>
   <consts>
      <code>
         <argcount> 0 </argcount>
         <nlocals> 3</nlocals>
         <stacksize> 3</stacksize>
         <flags> 004b</flags>
         <code>
            7824007c00006a0000830000445d16005c02007d01007d02007c01004748
            7c02004748710d005764000053
         </code>
         <dis>
  2           0 SETUP_LOOP              36 (to 39)
              3 LOAD_FAST                0 (kwargs)
              6 LOAD_ATTR                0 (iteritems)
              9 CALL_FUNCTION            0
             12 GET_ITER            
        >>   13 FOR_ITER                22 (to 38)
             16 UNPACK_SEQUENCE          2
             19 STORE_FAST               1 (k)
             22 STORE_FAST               2 (v)

  3          25 LOAD_FAST                1 (k)
             28 PRINT_ITEM          
             29 PRINT_NEWLINE       

  4          30 LOAD_FAST                2 (v)
             33 PRINT_ITEM          
             34 PRINT_NEWLINE       
             35 JUMP_ABSOLUTE           13
        >>   38 POP_BLOCK           
        >>   39 LOAD_CONST               0 (None)
             42 RETURN_VALUE        
         </dis>
         <names> ('iteritems',)</names>
         <varnames> ('kwargs', 'k', 'v')</varnames>
         <freevars> ()</freevars>
         <cellvars> ()</cellvars>
         <filename> 'test_kw_param.py'</filename>
         <name> 'foo'</name>
         <firstlineno> 1</firstlineno>
         <consts>
            None
         </consts>
         <lnotab> 000119010501</lnotab>
      </code>
      'a'
      1
      'b'
      2
      None
   </consts>
   <lnotab> 0906</lnotab>
</code>
