magic 03f30d0a
<code>
   <argcount> 0 </argcount>
   <nlocals> 0</nlocals>
   <stacksize> 2</stacksize>
   <flags> 0040</flags>
   <code> 6500006400006b020072140064010047486e000064020053</code>
   <dis>
  1           0 LOAD_NAME                0 (__name__)
              3 LOAD_CONST               0 ('__main__')
              6 COMPARE_OP               2 (==)
              9 POP_JUMP_IF_FALSE       20

  2          12 LOAD_CONST               1 ('hello')
             15 PRINT_ITEM          
             16 PRINT_NEWLINE       
             17 JUMP_FORWARD             0 (to 20)
        >>   20 LOAD_CONST               2 (None)
             23 RETURN_VALUE        
   </dis>
   <names> ('__name__',)</names>
   <varnames> ()</varnames>
   <freevars> ()</freevars>
   <cellvars> ()</cellvars>
   <filename> 'test_main_name.py'</filename>
   <name> '<module>'</name>
   <firstlineno> 1</firstlineno>
   <consts>
      '__main__'
      'hello'
      None
   </consts>
   <lnotab> 0c01</lnotab>
</code>
