magic 03f30d0a
<code>
   <argcount> 0 </argcount>
   <nlocals> 0</nlocals>
   <stacksize> 2</stacksize>
   <flags> 0040</flags>
   <code>
      6400008400005a00006500008300006401006b080072200065020047486e
      000064010053
   </code>
   <dis>
  1           0 LOAD_CONST               0 (<code object foo at 0x10b078c30, file "4_builtin_test.py", line 1>)
              3 MAKE_FUNCTION            0
              6 STORE_NAME               0 (foo)

  4           9 LOAD_NAME                0 (foo)
             12 CALL_FUNCTION            0
             15 LOAD_CONST               1 (None)
             18 COMPARE_OP               8 (is)
             21 POP_JUMP_IF_FALSE       32

  5          24 LOAD_NAME                2 (True)
             27 PRINT_ITEM          
             28 PRINT_NEWLINE       
             29 JUMP_FORWARD             0 (to 32)
        >>   32 LOAD_CONST               1 (None)
             35 RETURN_VALUE        
   </dis>
   <names> ('foo', 'None', 'True')</names>
   <varnames> ()</varnames>
   <freevars> ()</freevars>
   <cellvars> ()</cellvars>
   <filename> '4_builtin_test.py'</filename>
   <name> '<module>'</name>
   <firstlineno> 1</firstlineno>
   <consts>
      <code>
         <argcount> 0 </argcount>
         <nlocals> 0</nlocals>
         <stacksize> 1</stacksize>
         <flags> 0043</flags>
         <code> 64000053</code>
         <dis>
  2           0 LOAD_CONST               0 (None)
              3 RETURN_VALUE        
         </dis>
         <names> ()</names>
         <varnames> ()</varnames>
         <freevars> ()</freevars>
         <cellvars> ()</cellvars>
         <filename> '4_builtin_test.py'</filename>
         <name> 'foo'</name>
         <firstlineno> 1</firstlineno>
         <consts>
            None
         </consts>
         <lnotab> 0001</lnotab>
      </code>
      None
   </consts>
   <lnotab> 09030f01</lnotab>
</code>
