magic 03f30d0a
<code>
   <argcount> 0 </argcount>
   <nlocals> 0</nlocals>
   <stacksize> 2</stacksize>
   <flags> 0040</flags>
   <code>
      6400005a000065010065000083010047486401008400005a020065020065
      0000830100474864020053
   </code>
   <dis>
  1           0 LOAD_CONST               0 ('hello')
              3 STORE_NAME               0 (s)

  2           6 LOAD_NAME                1 (len)
              9 LOAD_NAME                0 (s)
             12 CALL_FUNCTION            1
             15 PRINT_ITEM          
             16 PRINT_NEWLINE       

  4          17 LOAD_CONST               1 (<code object py_len at 0x10644bc30, file "7_native_test.py", line 4>)
             20 MAKE_FUNCTION            0
             23 STORE_NAME               2 (py_len)

  7          26 LOAD_NAME                2 (py_len)
             29 LOAD_NAME                0 (s)
             32 CALL_FUNCTION            1
             35 PRINT_ITEM          
             36 PRINT_NEWLINE       
             37 LOAD_CONST               2 (None)
             40 RETURN_VALUE        
   </dis>
   <names> ('s', 'len', 'py_len')</names>
   <varnames> ()</varnames>
   <freevars> ()</freevars>
   <cellvars> ()</cellvars>
   <filename> '7_native_test.py'</filename>
   <name> '<module>'</name>
   <firstlineno> 1</firstlineno>
   <consts>
      'hello'
      <code>
         <argcount> 1 </argcount>
         <nlocals> 1</nlocals>
         <stacksize> 2</stacksize>
         <flags> 0043</flags>
         <code> 7400007c000083010053</code>
         <dis>
  5           0 LOAD_GLOBAL              0 (len)
              3 LOAD_FAST                0 (o)
              6 CALL_FUNCTION            1
              9 RETURN_VALUE        
         </dis>
         <names> ('len',)</names>
         <varnames> ('o',)</varnames>
         <freevars> ()</freevars>
         <cellvars> ()</cellvars>
         <filename> '7_native_test.py'</filename>
         <name> 'py_len'</name>
         <firstlineno> 4</firstlineno>
         <consts>
            None
         </consts>
         <lnotab> 0001</lnotab>
      </code>
      None
   </consts>
   <lnotab> 06010b020903</lnotab>
</code>
